LICENSE.txt
evo_package_news/__init__.py
evo_package_news/automation/api.yaml
evo_package_news/automation/entity.yaml
evo_package_news/control/CNewsApi.py
evo_package_news/control/__init__.py
evo_package_news/entity/ENewsInput.py
evo_package_news/entity/ENewsOutput.py
evo_package_news/entity/__init__.py
evo_package_news/utility/UNewsApi.py
evo_package_news/utility/__init__.py
evo_package_news-2024.10.22329.dist-info/LICENSE.txt
evo_package_news-2024.10.22329.dist-info/METADATA
evo_package_news-2024.10.22329.dist-info/WHEEL
evo_package_news-2024.10.22329.dist-info/RECORD
